zoomeye/__init__.py
zoomeye/cli.py
zoomeye/config.py
zoomeye/core.py
zoomeye/data.py
zoomeye/file.py
zoomeye/plotlib.py
zoomeye/sdk.py
zoomeye/show.py
zoomeye-2.2.0.dist-info/LICENSE
zoomeye-2.2.0.dist-info/METADATA
zoomeye-2.2.0.dist-info/WHEEL
zoomeye-2.2.0.dist-info/entry_points.txt
zoomeye-2.2.0.dist-info/top_level.txt
zoomeye-2.2.0.dist-info/RECORD
